siglo.py
siglo-1.0.4.dist-info/LICENSE.txt
siglo-1.0.4.dist-info/METADATA
siglo-1.0.4.dist-info/WHEEL
siglo-1.0.4.dist-info/top_level.txt
siglo-1.0.4.dist-info/RECORD
