Metadata-Version: 2.1
Name: siglo
Version: 1.0.4
Summary: SigLo camera-based gesture detection
Author: Andrey Piterkin, Nishil Patel, Ryan Saperstein, Suraj Ramchandran
License: UNKNOWN
Platform: UNKNOWN
Classifier: Programming Language :: Python :: 3
Classifier: License :: OSI Approved :: MIT License
Classifier: Operating System :: OS Independent
Requires-Python: >=3.9
License-File: LICENSE.txt
Requires-Dist: opencv-python
Requires-Dist: mediapipe
Requires-Dist: pynput
